pyPSG/__init__.py
pyPSG/pypsg_example.py
pyPSG/utils.py
pyPSG/IO/__init__.py
pyPSG/IO/data_handling.py
pyPSG/IO/edf_cut.py
pyPSG/IO/edf_read.py
pyPSG/IO/plot.py
pyPSG/biomarkers/__init__.py
pyPSG/biomarkers/all_BMs.py
pyPSG/biomarkers/get_ecg_bm.py
pyPSG/biomarkers/get_hrv_bm.py
pyPSG/biomarkers/get_ppg_bm.py
pyPSG/biomarkers/get_spo2_bm.py
pyPSG/biomarkers/hrv_bms.py
pypsg_toolbox-1.0.8.dist-info/licenses/LICENSE.txt
pypsg_toolbox-1.0.8.dist-info/METADATA
pypsg_toolbox-1.0.8.dist-info/WHEEL
pypsg_toolbox-1.0.8.dist-info/top_level.txt
pypsg_toolbox-1.0.8.dist-info/RECORD
